README.txt
setup.py
django_flashcookie.egg-info/PKG-INFO
django_flashcookie.egg-info/SOURCES.txt
django_flashcookie.egg-info/dependency_links.txt
django_flashcookie.egg-info/top_level.txt
flashcookie/__init__.py
flashcookie/context_processors.py
flashcookie/middleware.py