Metadata-Version: 1.0
Name: django-flashcookie
Version: 0.1.5
Summary: This django application provides rails-like flash messages to Django framework.
Home-page: http://bitbucket.org/offline/django-flashcookie/wiki/Home
Author: Anderson
Author-email: self.anderson@gmail.com
License: BSD
Keywords: django
Platform: UNKNOWN
